LICENSE.txt
README.md
setup.cfg
setup.py
Argumental/Argue.py
Argumental/Argument.py
Argumental/Attribute.py
Argumental/Command.py
Argumental/Getters.py
Argumental/NamedShort.py
Argumental/Operation.py
Argumental/Parameter.py
Argumental/Returns.py
Argumental/Value.py
Argumental/__init__.py
Argumental.egg-info/PKG-INFO
Argumental.egg-info/SOURCES.txt
Argumental.egg-info/dependency_links.txt
Argumental.egg-info/requires.txt
Argumental.egg-info/top_level.txt