Metadata-Version: 2.1
Name: Argumental
Version: 1.13
Summary: UNKNOWN
Home-page: https://github.com/eddo888/argumental
Author: David Edson
Author-email: eddo888@tpg.com.au
License: MIT
Download-URL: https://github.com/eddo888/argumental/archive/1.13.tar.gz
Platform: UNKNOWN
